conversation_control/__init__.py
conversation_control-0.1.2.dist-info/LICENSE.txt
conversation_control-0.1.2.dist-info/METADATA
conversation_control-0.1.2.dist-info/WHEEL
conversation_control-0.1.2.dist-info/pyproject
conversation_control-0.1.2.dist-info/top_level.txt
conversation_control-0.1.2.dist-info/RECORD
